immuno_probs/__init__.py
immuno_probs/alignment/__init__.py
immuno_probs/alignment/muscle_aligner.py
immuno_probs/cdr3/__init__.py
immuno_probs/cdr3/anchor_locator.py
immuno_probs/cdr3/olga_container.py
immuno_probs/cli/__init__.py
immuno_probs/cli/__main__.py
immuno_probs/cli/build_igor_model.py
immuno_probs/cli/convert_adaptive_sequences.py
immuno_probs/cli/evaluate_sequences.py
immuno_probs/cli/generate_sequences.py
immuno_probs/cli/locate_cdr3_anchors.py
immuno_probs/config/default.ini
immuno_probs/convert/__init__.py
immuno_probs/convert/adaptive_sequence_convertor.py
immuno_probs/data/human_b_heavy/IGHD.fasta
immuno_probs/data/human_b_heavy/IGHJ.fasta
immuno_probs/data/human_b_heavy/IGHV.fasta
immuno_probs/data/human_b_heavy/J_gene_CDR3_anchors.tsv
immuno_probs/data/human_b_heavy/V_gene_CDR3_anchors.tsv
immuno_probs/data/human_b_heavy/model_marginals.txt
immuno_probs/data/human_b_heavy/model_params.txt
immuno_probs/data/human_t_alpha/J_gene_CDR3_anchors.tsv
immuno_probs/data/human_t_alpha/TRAJ.fasta
immuno_probs/data/human_t_alpha/TRAV.fasta
immuno_probs/data/human_t_alpha/V_gene_CDR3_anchors.tsv
immuno_probs/data/human_t_alpha/model_marginals.txt
immuno_probs/data/human_t_alpha/model_params.txt
immuno_probs/data/human_t_beta/J_gene_CDR3_anchors.tsv
immuno_probs/data/human_t_beta/TRBD.fasta
immuno_probs/data/human_t_beta/TRBJ.fasta
immuno_probs/data/human_t_beta/TRBV.fasta
immuno_probs/data/human_t_beta/V_gene_CDR3_anchors.tsv
immuno_probs/data/human_t_beta/model_marginals.txt
immuno_probs/data/human_t_beta/model_params.txt
immuno_probs/data/mouse_t_beta/J_gene_CDR3_anchors.tsv
immuno_probs/data/mouse_t_beta/TRBD.fasta
immuno_probs/data/mouse_t_beta/TRBJ.fasta
immuno_probs/data/mouse_t_beta/TRBV.fasta
immuno_probs/data/mouse_t_beta/V_gene_CDR3_anchors.tsv
immuno_probs/data/mouse_t_beta/model_marginals.txt
immuno_probs/data/mouse_t_beta/model_params.txt
immuno_probs/model/__init__.py
immuno_probs/model/default_models.py
immuno_probs/model/igor_interface.py
immuno_probs-0.2.1.dist-info/LICENSE
immuno_probs-0.2.1.dist-info/METADATA
immuno_probs-0.2.1.dist-info/WHEEL
immuno_probs-0.2.1.dist-info/entry_points.txt
immuno_probs-0.2.1.dist-info/top_level.txt
immuno_probs-0.2.1.dist-info/RECORD
