Metadata-Version: 2.1
Name: immuno-probs
Version: 0.2.1
Summary: Create IGoR models and calculate the generation probability of V(D)J and CDR3 sequences.
Home-page: https://github.com/penuts7644/immuno-probs
Author: Wout van Helvoirt
Author-email: wout.van.helvoirt@icloud.com
License: UNKNOWN
Project-URL: Bug Reports, https://github.com/penuts7644/immuno-probs/issues
Keywords: Bio-Informatics,Recombination,Sequencing,Analysis,DNA,Model,Genes,Kmer,Immune,Probs,Probability
Platform: UNKNOWN
Classifier: Development Status :: 4 - Beta
Classifier: Intended Audience :: Developers
Classifier: Intended Audience :: Science/Research
Classifier: License :: OSI Approved :: GNU General Public License v3 (GPLv3)
Classifier: Natural Language :: English
Classifier: Operating System :: OS Independent
Classifier: Programming Language :: Python
Classifier: Programming Language :: Python :: 2
Classifier: Programming Language :: Python :: 2.7
Classifier: Topic :: Scientific/Engineering :: Bio-Informatics
Classifier: Topic :: Scientific/Engineering :: Information Analysis
Classifier: Topic :: Scientific/Engineering :: Medical Science Apps.
Requires-Dist: numpy (==1.16.5)
Requires-Dist: pandas (==0.24.*)
Requires-Dist: scipy (==1.2.2)
Requires-Dist: matplotlib (==2.2.4)
Requires-Dist: biopython (==1.75)
Requires-Dist: pathos (>=0.2.2.1)
Requires-Dist: olga (>=1.0.2)
Provides-Extra: development
Requires-Dist: twine (==1.15.0) ; extra == 'development'
